{
    "parish_name": "St. Anthony’s Chapel of Bengaluru",
    "parish_city": "Austin Town, Bengaluru, KA",
    "mass_times": "Sunday: 8:00 AM, 10:30 AM\nMon-Sat 7:30 AM\nSaturday Vigil: 4:45PM\nFirst Fridays: 7:00PM",
    "parish_address": "St. Anthony’s Chapel (Estd 1908), Cement Line, Bengaluru 560 047, C/o Sacred Heart Church, Richmond Road.",
    "announcements": "Advent penance service on Dec 12 at 7 PM.\nChoir rehearsal Thursdays at 6:30 PM.",
    "contact_phone": "+91 1234-123456",
    "contact_email": "fatherraman@bangalorearchdiocese.org",
    "use_liturgical_colors": true
}
